KratosMultilevelMonteCarloApplication-9.3.2.dist-info/METADATA
KratosMultilevelMonteCarloApplication-9.3.2.dist-info/WHEEL
KratosMultilevelMonteCarloApplication-9.3.2.dist-info/top_level.txt
KratosMultilevelMonteCarloApplication-9.3.2.dist-info/RECORD
KratosMultilevelMonteCarloApplication.libs/libKratosMultilevelMonteCarloCore-d340051f.so
KratosMultiphysics/.libs/libKratosMultilevelMonteCarloCore.so
KratosMultiphysics/.libs/KratosMultilevelMonteCarloApplication.cpython-38-x86_64-linux-gnu.so
KratosMultiphysics/MultilevelMonteCarloApplication/generator_utilities.py
KratosMultiphysics/MultilevelMonteCarloApplication/mlmc_utilities.py
KratosMultiphysics/MultilevelMonteCarloApplication/tools.py
KratosMultiphysics/MultilevelMonteCarloApplication/mc_utilities.py
KratosMultiphysics/MultilevelMonteCarloApplication/adaptive_refinement_utilities.py
KratosMultiphysics/MultilevelMonteCarloApplication/__init__.py
KratosMultiphysics/MultilevelMonteCarloApplication/statistical_variable_utilities.py
KratosMultiphysics/MultilevelMonteCarloApplication/PyCOMPSs/exaqute/__init__.py
KratosMultiphysics/MultilevelMonteCarloApplication/PyCOMPSs/exaqute/common/consts.py
KratosMultiphysics/MultilevelMonteCarloApplication/PyCOMPSs/exaqute/common/exception.py
KratosMultiphysics/MultilevelMonteCarloApplication/PyCOMPSs/exaqute/common/__init__.py
KratosMultiphysics/MultilevelMonteCarloApplication/PyCOMPSs/exaqute/local/decorators.py
KratosMultiphysics/MultilevelMonteCarloApplication/PyCOMPSs/exaqute/local/internals.py
KratosMultiphysics/MultilevelMonteCarloApplication/PyCOMPSs/exaqute/local/consts.py
KratosMultiphysics/MultilevelMonteCarloApplication/PyCOMPSs/exaqute/local/functions.py
KratosMultiphysics/MultilevelMonteCarloApplication/PyCOMPSs/exaqute/local/__init__.py
KratosMultiphysics/MultilevelMonteCarloApplication/XMC/xmc/errorEstimator.py
KratosMultiphysics/MultilevelMonteCarloApplication/XMC/xmc/localEnvironment.py
KratosMultiphysics/MultilevelMonteCarloApplication/XMC/xmc/estimationAssembler.py
KratosMultiphysics/MultilevelMonteCarloApplication/XMC/xmc/randomGeneratorWrapper.py
KratosMultiphysics/MultilevelMonteCarloApplication/XMC/xmc/bayesianEstimator.py
